sample/__init__.py
sample/mysql.py
dixeam_mysql-2.0.0.dist-info/LICENSE.txt
dixeam_mysql-2.0.0.dist-info/METADATA
dixeam_mysql-2.0.0.dist-info/WHEEL
dixeam_mysql-2.0.0.dist-info/entry_points.txt
dixeam_mysql-2.0.0.dist-info/top_level.txt
dixeam_mysql-2.0.0.dist-info/RECORD
