Metadata-Version: 2.1
Name: dixeam-mysql
Version: 2.0.0
Summary: A sample Python project
Home-page: https://github.com/pypa/dixeam_mysql
Author: Qaiser Shakoor
Author-email: link2qaiser@gmail.com
License: UNKNOWN
Project-URL: Bug Reports, https://github.com/zain-dixeam26/dixeam_mysql/issues
Project-URL: Source, https://github.com/zain-dixeam26/dixeam_mysql/
Platform: UNKNOWN
Classifier: Development Status :: 3 - Alpha
Classifier: Intended Audience :: Developers
Classifier: Topic :: Software Development :: Build Tools
Classifier: License :: OSI Approved :: MIT License
Classifier: Programming Language :: Python :: 3
Classifier: Programming Language :: Python :: 3.6
Classifier: Programming Language :: Python :: 3.7
Classifier: Programming Language :: Python :: 3.8
Classifier: Programming Language :: Python :: 3.9
Classifier: Programming Language :: Python :: 3.10
Classifier: Programming Language :: Python :: 3 :: Only
Requires-Python: >=3.6, <4
License-File: LICENSE.txt
Requires-Dist: peppercorn
Requires-Dist: PyMySQL
Requires-Dist: SQLAlchemy
Provides-Extra: dev
Requires-Dist: check-manifest ; extra == 'dev'
Provides-Extra: test
Requires-Dist: coverage ; extra == 'test'
